{
  "project_info": {
    "project_number": "921348313705",
    "project_id": "proj-flutter-restapi",
    "storage_bucket": "proj-flutter-restapi.appspot.com"
  },
  "client": [
    {
      "client_info": {
        "mobilesdk_app_id": "1:921348313705:android:35c08d41f7d9d861a248f8",
        "android_client_info": {
          "package_name": "br.edu.infnet.projetoacademia"
        }
      },
      "oauth_client": [
        {
          "client_id": "921348313705-sgbvm2qcgrjcem2vjeq5cms8iav0dhib.apps.googleusercontent.com",
          "client_type": 3
        }
      ],
      "api_key": [
        {
          "current_key": "AIzaSyD9eL_XL-ZOjy7TPFP66w8L3ztQaBZeKZQ"
        }
      ],
      "services": {
        "appinvite_service": {
          "other_platform_oauth_client": [
            {
              "client_id": "921348313705-sgbvm2qcgrjcem2vjeq5cms8iav0dhib.apps.googleusercontent.com",
              "client_type": 3
            }
          ]
        }
      }
    }
  ],
  "configuration_version": "1"
}